quicklib/__init__.py
quicklib/bootstrap.py
quicklib/commands.py
quicklib/datafiles.py
quicklib/incorporator.py
quicklib/quicklib_incorporated.zip
quicklib/requirements.py
quicklib/scripting.py
quicklib/setupapi.py
quicklib/utils.py
quicklib/version.py
quicklib/versioning.py
quicklib/virtualfiles.py
quicklib/cli/__init__.py
quicklib/cli/quicklibsetup.py
quicklib/cli/setupyml.py
quicklib-2.5.dist-info/LICENSE.md
quicklib-2.5.dist-info/METADATA
quicklib-2.5.dist-info/WHEEL
quicklib-2.5.dist-info/entry_points.txt
quicklib-2.5.dist-info/top_level.txt
quicklib-2.5.dist-info/RECORD
