Metadata-Version: 2.1
Name: quicklib
Version: 2.5
Summary: quicklib: hassle-free setup scripts for your python libraries
Home-page: https://github.com/yonatanp/quicklib
Author: Yonatan Perry
Author-email: yonatan.perry@gmail.com
License: MIT
Platform: any
Classifier: Development Status :: 5 - Production/Stable
Classifier: Programming Language :: Python
Classifier: Programming Language :: Python :: 3
Classifier: License :: OSI Approved :: MIT License
Classifier: Natural Language :: English
Classifier: Intended Audience :: Developers
Classifier: Topic :: Software Development :: Build Tools
Classifier: Topic :: Software Development :: Libraries :: Python Modules
Classifier: Operating System :: OS Independent
Requires-Python: >=3.7
Requires-Dist: yarg (~=0.1.9)
Requires-Dist: PyYAML (>=4.2b1)
